railcmd/__init__.py
railcmd/base.py
railcmd/connection.py
railcmd/exceptions.py
railcmd/loco.py
railcmd-0.0.1.dist-info/LICENSE
railcmd-0.0.1.dist-info/METADATA
railcmd-0.0.1.dist-info/WHEEL
railcmd-0.0.1.dist-info/top_level.txt
railcmd-0.0.1.dist-info/RECORD
